file_validation_decorator/__init__.py
file_validation_decorator/file_validation.py
file_validation_decorator-0.0.8.dist-info/METADATA
file_validation_decorator-0.0.8.dist-info/WHEEL
file_validation_decorator-0.0.8.dist-info/top_level.txt
file_validation_decorator-0.0.8.dist-info/RECORD
