Metadata-Version: 2.1
Name: file-validation-decorator
Version: 0.0.8
Summary: This decorator validates the file extension and file size of an in memory file object.
Home-page: https://github.com/JustinShuttleworth/file_validation_decorator
Author: Justin Shuttleworth
Author-email: justin_shuttleworth@outlook.com
License: UNKNOWN
Project-URL: Bug Tracker, https://github.com/pypa/sampleproject/issues
Platform: UNKNOWN
Classifier: Programming Language :: Python :: 3
Classifier: License :: OSI Approved :: MIT License
Classifier: Operating System :: OS Independent
Requires-Python: >=3.6
